hl_ff_api/__init__.py
hl_ff_api/client.py
hl_ff_api-2.3.4.dist-info/licenses/LICENSE
hl_ff_api-2.3.4.dist-info/METADATA
hl_ff_api-2.3.4.dist-info/WHEEL
hl_ff_api-2.3.4.dist-info/top_level.txt
hl_ff_api-2.3.4.dist-info/RECORD
