Metadata-Version: 2.4
Name: hl_ff_api
Version: 2.3.4
Summary: Python client library for HL Gaming Official Free Fire API
Home-page: https://www.hlgamingofficial.com/p/api.html
Author: Haroon Brokha
Author-email: developers@hlgamingofficial.com
Project-URL: Documentation, https://www.hlgamingofficial.com/p/free-fire-api-data-documentation.html
Project-URL: Homepage, https://www.hlgamingofficial.com
Classifier: Programming Language :: Python :: 3
Classifier: Operating System :: OS Independent
Classifier: License :: OSI Approved :: MIT License
Classifier: Topic :: Software Development :: Libraries :: Python Modules
Requires-Python: >=3.6
License-File: LICENSE
Requires-Dist: requests
Dynamic: author
Dynamic: author-email
Dynamic: classifier
Dynamic: description
Dynamic: description-content-type
Dynamic: home-page
Dynamic: license-file
Dynamic: project-url
Dynamic: requires-dist
Dynamic: requires-python
Dynamic: summary
